zoot/automation/common.py
zoot/automation/drivers.py
zoot/automation/elements.py
zoot/automation/environments.py
zoot/automation/pages.py
zoot/automation/wait.py
zoot/automation/mobile/common.py
zoot/automation/mobile/drivers.py
zoot/bdd/common.py
zoot/bdd/decorators.py
zoot/bdd/environments.py
zoot/bdd/executors.py
zoot/bdd/main.py
zoot/bdd/reporting.py
zoot/testing/common.py
zoot/testing/context.py
zoot/testing/environments.py
zoot/testing/executors.py
zoot/testing/reporting.py
zoot/utils/collections.py
zoot/utils/files.py
zoot/utils/strings.py
zoot-0.0.6.dist-info/LICENSE.txt
zoot-0.0.6.dist-info/METADATA
zoot-0.0.6.dist-info/WHEEL
zoot-0.0.6.dist-info/entry_points.txt
zoot-0.0.6.dist-info/top_level.txt
zoot-0.0.6.dist-info/RECORD
