Metadata-Version: 2.1
Name: zoot
Version: 0.0.6
Summary: Web automation and REST API testing framework
Home-page: https://github.com/brentlamarrayjr/zoot-py
Author: Brent Ray
Author-email: brentlamarrayjr@gmail.com
License: UNKNOWN
Keywords: testing,api,json,validation,automation,framework
Platform: UNKNOWN
Classifier: Programming Language :: Python :: 3
Classifier: License :: OSI Approved :: Mozilla Public License 2.0 (MPL 2.0)
Classifier: Operating System :: OS Independent
